{
  "asOf": "2026-06-27",
  "source": "المخزون حتي تاريخ 27-06-2026.pdf",
  "rows": [
    {
      "item": "عاصمة الدجاج فيليه هندي كامل",
      "cartons": 1500,
      "supplier": ""
    },
    {
      "item": "عاصمة الدجاج توب سايد هندي كامل",
      "cartons": 1,
      "supplier": ""
    },
    {
      "item": "عاصمة الدجاج رامب ستيك رستم",
      "cartons": 9,
      "supplier": ""
    },
    {
      "item": "عاصمة الدجاج فيليه عجل الممتاز",
      "cartons": 5,
      "supplier": ""
    },
    {
      "item": "عاصمة الدجاج فور كوارتر هندي كامل",
      "cartons": 1500,
      "supplier": ""
    },
    {
      "item": "عاصمة الدجاج شاورما دجاج لارا 2.5ك",
      "cartons": 2248,
      "supplier": ""
    },
    {
      "item": "صدور دجاج برازيلي مجمد",
      "cartons": 2685,
      "supplier": ""
    }
  ]
}
